aioprometheus_summary/__init__.py
aioprometheus_summary/version.py
aioprometheus_summary-0.1.0.dist-info/LICENSE
aioprometheus_summary-0.1.0.dist-info/METADATA
aioprometheus_summary-0.1.0.dist-info/WHEEL
aioprometheus_summary-0.1.0.dist-info/top_level.txt
aioprometheus_summary-0.1.0.dist-info/RECORD
